__init__.py
inferent/__init__.py
inferent/ratings.py
inferent/scraping/__init__.py
inferent/scraping/base_scraper.py
inferent/scraping/utils.py
inferent/utils/__init__.py
inferent/utils/betting.py
inferent/utils/functions.py
inferent/utils/math.py
inferent/utils/strings.py
tests/__init__.py
tests/test_ratings.py
tests/scraping/__init__.py
tests/scraping/test_base_scraper.py
tests/scraping/test_utils.py
tests/utils/__init__.py
tests/utils/test_betting.py
tests/utils/test_functions.py
tests/utils/test_math.py
tests/utils/test_strings.py
inferent-0.1.5.dist-info/LICENSE
inferent-0.1.5.dist-info/METADATA
inferent-0.1.5.dist-info/WHEEL
inferent-0.1.5.dist-info/top_level.txt
inferent-0.1.5.dist-info/RECORD
