Metadata-Version: 2.1
Name: inferent
Version: 0.1.5
Summary: Inferent Ventures
Author-email: Inferent Ventures <inferentventures@gmail.com>
Project-URL: Homepage, https://github.com/inferent
Project-URL: Issues, https://github.com/inferent
Classifier: Programming Language :: Python :: 3
Classifier: License :: OSI Approved :: MIT License
Classifier: Operating System :: OS Independent
Requires-Python: >=3.8
License-File: LICENSE
Requires-Dist: parsel
Requires-Dist: selenium
Requires-Dist: pandas
Requires-Dist: scipy
Requires-Dist: trueskill
